{"IsLog":true,"IsStop":false,"ListDetails":[{"ID":"eef6b9f5-eb1c-469e-a0b0-47d021cebe2f","FileName":"data0","SpreadsheetID":"1Ln6hwAS31EII2XdlWN9PN0kaNEt4S3RIZewf81w-ePQ","SpreadsheetName":"0","UploadFolder":"D:\\New folder\\0.csv","IsFile":true,"HandlerLink":"http://svn.3ps.vn:15002/Handler/UploadFile.ashx","HandlerKey":"data0","ColumnValueStart":3,"ColumnValueEnd":39,"RowValueStart":2,"RowValueEnd":174,"ColumnTitle":1,"RowTitle":1,"LinkData":"http://svn.3ps.vn:15002/api/Data/SendData","LinkPush":"http://svn.3ps.vn:15002/api/Data/SendPushByData","FormatPushTitle":"data change [listrowtitle]","FormatPushBody":"sadsadsad"},{"ID":"0ae731ae-1996-4884-b068-ba35ef161381","FileName":"data1","SpreadsheetID":"1Ln6hwAS31EII2XdlWN9PN0kaNEt4S3RIZewf81w-ePQ","SpreadsheetName":"1","UploadFolder":"D:\\New folder\\1.csv","IsFile":true,"HandlerLink":"http://svn.3ps.vn:15002/Handler/UploadFile.ashx","HandlerKey":"data1","ColumnValueStart":3,"ColumnValueEnd":20,"RowValueStart":2,"RowValueEnd":860,"ColumnTitle":1,"RowTitle":1,"LinkData":"http://svn.3ps.vn:15002/api/Data/SendData","LinkPush":"http://svn.3ps.vn:15002/api/Data/SendPushByData","FormatPushTitle":"data change [listrowtitle]","FormatPushBody":"sadsadsad\r\n"}]}